[
  {
    "guildId": "1263545537303416863",
    "totalCount": {
      "current": 451,
      "total": 451
    },
    "eventCount": {
      "current": {
        "messageCreate": 31,
        "messageUpdate": 1
      },
      "total": {
        "messageCreate": 31,
        "messageUpdate": 1
      }
    },
    "commandCount": {
      "current": {
        "developing": {
          "database": 1,
          "reply": 1
        },
        "misc": {
          "bark": 2,
          "level": 367,
          "userage": 3
        },
        "moderation": {
          "lvsys": 19
        }
      },
      "total": {
        "developing": {
          "database": 1,
          "reply": 1
        },
        "misc": {
          "bark": 2,
          "level": 367,
          "userage": 3
        },
        "moderation": {
          "lvsys": 19
        }
      }
    },
    "levelSystemCount": {
      "current": {
        "xp": 235,
        "levels": 3
      },
      "total": {
        "xp": 235,
        "levels": 3
      }
    },
    "deletionDate": null
  }
]